odoo/addons/purchase_picking_state/README.rst
odoo/addons/purchase_picking_state/__init__.py
odoo/addons/purchase_picking_state/__manifest__.py
odoo/addons/purchase_picking_state/i18n/de.po
odoo/addons/purchase_picking_state/i18n/es.po
odoo/addons/purchase_picking_state/i18n/es_PE.po
odoo/addons/purchase_picking_state/i18n/fr.po
odoo/addons/purchase_picking_state/i18n/fr_BE.po
odoo/addons/purchase_picking_state/i18n/gl.po
odoo/addons/purchase_picking_state/i18n/hr.po
odoo/addons/purchase_picking_state/i18n/it.po
odoo/addons/purchase_picking_state/i18n/nl.po
odoo/addons/purchase_picking_state/i18n/nl_NL.po
odoo/addons/purchase_picking_state/i18n/pt_BR.po
odoo/addons/purchase_picking_state/i18n/purchase_picking_state.pot
odoo/addons/purchase_picking_state/i18n/ro.po
odoo/addons/purchase_picking_state/i18n/sl.po
odoo/addons/purchase_picking_state/i18n/vi_VN.po
odoo/addons/purchase_picking_state/models/__init__.py
odoo/addons/purchase_picking_state/models/purchase.py
odoo/addons/purchase_picking_state/readme/CONTRIBUTORS.rst
odoo/addons/purchase_picking_state/readme/DESCRIPTION.rst
odoo/addons/purchase_picking_state/readme/USAGE.rst
odoo/addons/purchase_picking_state/static/description/icon.png
odoo/addons/purchase_picking_state/static/description/index.html
odoo/addons/purchase_picking_state/tests/__init__.py
odoo/addons/purchase_picking_state/tests/test_purchase_picking_state.py
odoo/addons/purchase_picking_state/views/purchase_view.xml
odoo12_addon_purchase_picking_state-12.0.1.1.0.dist-info/METADATA
odoo12_addon_purchase_picking_state-12.0.1.1.0.dist-info/WHEEL
odoo12_addon_purchase_picking_state-12.0.1.1.0.dist-info/top_level.txt
odoo12_addon_purchase_picking_state-12.0.1.1.0.dist-info/RECORD
